{
  "site_info": {
    "name": "Texly",
    "url": "https://www.texlyonline.in",
    "description_en": "Free AI, Text, PDF, and Image tools platform",
    "description_hi": "मुफ्त AI, टेक्स्ट, PDF और इमेज टूल्स प्लेटफॉर्म",
    "primary_languages": ["en", "hi"]
  },
  "global_messages": {
    "welcome_en": "Hi! I'm Texly AI 👋 Need help with any tool?",
    "welcome_hi": "नमस्ते! मैं Texly AI हूं 👋 किसी टूल में मदद चाहिए?",
    "quick_help_en": "Ask me: 'Remove image background', 'PDF to Word', or 'Count words'",
    "quick_help_hi": "मुझसे पूछें: 'बैकग्राउंड हटाएं', 'PDF से Word', या 'शब्द गिनें'",
    "not_found_en": "I couldn't find that tool. Try these popular ones:",
    "not_found_hi": "मुझे वह टूल नहीं मिला। ये लोकप्रिय टूल आज़माएं:"
  },
  "tool_categories": [
    { "slug": "ai-tools", "name_en": "AI Tools", "name_hi": "AI टूल्स", "icon": "🤖" },
    { "slug": "text-tools", "name_en": "Text Tools", "name_hi": "टेक्स्ट टूल्स", "icon": "📝" },
    { "slug": "pdf-tools", "name_en": "PDF Tools", "name_hi": "PDF टूल्स", "icon": "📄" },
    { "slug": "image-tools", "name_en": "Image Tools", "name_hi": "इमेज टूल्स", "icon": "🖼️" },
    { "slug": "converter-tools", "name_en": "Converters", "name_hi": "कन्वर्टर्स", "icon": "🔄" },
    { "slug": "developer-tools", "name_en": "Dev Tools", "name_hi": "डेव टूल्स", "icon": "💻" },
    { "slug": "formatter-tools", "name_en": "Formatters", "name_hi": "फॉर्मेटर्स", "icon": "✨" },
    { "slug": "utility-tools", "name_en": "Utility", "name_hi": "उपयोगिता", "icon": "🔧" }
  ],
  "tools": [
    {
      "tool_name": "Face Swap",
      "slug": "face-swap",
      "url": "https://www.texlyonline.in/tools/face-swap",
      "category": "ai-tools",
      "description_en": "Swap faces in photos instantly with AI",
      "description_hi": "AI से फोटो में तुरंत चेहरा बदलें",
      "keywords": ["face swap", "swap face", "face changer", "ai face swap", "celebrity face swap", "चेहरा बदलें", "फेस स्वैप"],
      "search_terms": ["change face", "face replacement", "my face on another photo"],
      "common_user_problems": ["faces not aligning", "multiple people confusing", "poor quality result"],
      "tool_intro_messages_en": ["Upload a face photo and target photo. I'll swap them! 🎭", "Want to become a celebrity? Try Face Swap!"],
      "tool_intro_messages_hi": ["फेस फोटो और टार्गेट फोटो अपलोड करें। मैं स्वैप कर दूंगा! 🎭", "सेलिब्रिटी बनना चाहते हैं? फेस स्वैप आज़माएं!"],
      "success_messages_en": ["Face swapped successfully! Looks amazing! 🎉", "Your face swap is ready! Save it below ✨"],
      "success_messages_hi": ["चेहरा सफलतापूर्वक बदला! बहुत बढ़िया! 🎉", "आपका फेस स्वैप तैयार है! नीचे सेव करें ✨"],
      "error_messages_en": ["Couldn't detect a clear face. Try another photo with good lighting.", "Processing failed. Try refreshing the page."],
      "error_messages_hi": ["स्पष्ट चेहरा नहीं मिला। अच्छी रोशनी वाली दूसरी फोटो आज़माएं।", "प्रोसेसिंग फेल हुई। पेज रिफ्रेश करके देखें।"],
      "fallback_messages_en": ["Face swap not working? Try BG Remover or Image Enhancer instead! 💡", "Try using a clearer front-facing photo for better results."],
      "fallback_messages_hi": ["फेस स्वैप काम नहीं कर रहा? बीजी रिमूवर या इमेज एन्हांसर आज़माएं! 💡", "बेहतर रिजल्ट के लिए साफ फ्रंट-फेसिंग फोटो आज़माएं।"],
      "related_tools": ["bg-remover", "enhancer"],
      "alternative_tools": ["bg-remover", "image-upscale"],
      "recommended_tools": ["image-generator", "enhancer"],
      "user_guidance_en": ["Upload a clear face photo (front-facing)", "Target photo should have at least one face", "Click 'Swap Now' and wait 5-10 seconds"],
      "user_guidance_hi": ["साफ चेहरे वाली फोटो अपलोड करें (सामने से)", "लक्ष्य फोटो में कम से कम एक चेहरा होना चाहिए", "'Swap Now' पर क्लिक करें और 5-10 सेकंड प्रतीक्षा करें"],
      "engagement_messages_en": ["Did you know? You can swap with movie posters too! 🎬", "Create funny memes with Face Swap!"],
      "engagement_messages_hi": ["क्या आप जानते हैं? मूवी पोस्टर के साथ भी स्वैप कर सकते हैं! 🎬", "फेस स्वैप से मजेदार मीम्स बनाएं!"]
    },
    {
      "tool_name": "BG Remover",
      "slug": "bg-remover",
      "url": "https://www.texlyonline.in/tools/bg-remover",
      "category": "image-tools",
      "description_en": "Remove image background in 1 click",
      "description_hi": "1 क्लिक में इमेज बैकग्राउंड हटाएं",
      "keywords": ["background remover", "remove background", "transparent background", "bg remover", "image cutout", "बैकग्राउंड हटाएं"],
      "search_terms": ["remove background", "transparent image", "cut out image", "white background removal"],
      "common_user_problems": ["edges not smooth", "slow processing", "complex background fails"],
      "tool_intro_messages_en": ["Remove any background instantly! Just upload your image 🖼️", "Need a transparent product photo? I'll do it in seconds!"],
      "tool_intro_messages_hi": ["तुरंत बैकग्राउंड हटाएं! बस इमेज अपलोड करें 🖼️", "पारदर्शी प्रोडक्ट फोटो चाहिए? मैं सेकंडों में कर दूंगा!"],
      "success_messages_en": ["Background removed! Perfect for your project ✨", "Done! Download your transparent image below 🎉"],
      "success_messages_hi": ["बैकग्राउंड हटा दिया! आपके प्रोजेक्ट के लिए परफेक्ट ✨", "हो गया! पारदर्शी इमेज नीचे डाउनलोड करें 🎉"],
      "error_messages_en": ["Couldn't process this image. Try a simpler background.", "File too large. Max 5MB for free use."],
      "error_messages_hi": ["यह इमेज प्रोसेस नहीं कर सका। सिंपल बैकग्राउंड आज़माएं।", "फाइल बहुत बड़ी है। फ्री यूज के लिए अधिकतम 5MB।"],
      "fallback_messages_en": ["BG Remover stuck? Try Image Enhancer to improve quality first! 💡", "For better results, use images with solid color backgrounds."],
      "fallback_messages_hi": ["BG रिमूवर अटक गया? पहले इमेज एन्हांसर से क्वालिटी सुधारें! 💡", "बेहतर परिणामों के लिए, सॉलिड कलर बैकग्राउंड वाली इमेज का उपयोग करें।"],
      "related_tools": ["enhancer", "compressor"],
      "alternative_tools": ["face-swap", "image-upscale"],
      "recommended_tools": ["enhancer", "image-to-pdf-converter"],
      "user_guidance_en": ["Upload JPG or PNG (max 5MB)", "Wait 3-5 seconds", "Download PNG with transparent background"],
      "user_guidance_hi": ["JPG या PNG अपलोड करें (अधिकतम 5MB)", "3-5 सेकंड प्रतीक्षा करें", "पारदर्शी बैकग्राउंड वाली PNG डाउनलोड करें"],
      "engagement_messages_en": ["Pro tip: Use on product photos for best results! 🛍️", "Removed 1M+ backgrounds already! 🚀"],
      "engagement_messages_hi": ["प्रो टिप: बेहतर परिणामों के लिए प्रोडक्ट फोटो पर उपयोग करें! 🛍️", "पहले ही 1M+ बैकग्राउंड हटा चुके हैं! 🚀"]
    },
    {
      "tool_name": "Image Enhancer",
      "slug": "enhancer",
      "url": "https://www.texlyonline.in/tools/enhancer",
      "category": "image-tools",
      "description_en": "Enhance image quality with AI",
      "description_hi": "AI से इमेज क्वालिटी बढ़ाएं",
      "keywords": ["image enhancer", "improve image quality", "sharpen image", "enhance photo", "इमेज एन्हांसर"],
      "search_terms": ["make image clearer", "fix blurry photo", "improve photo quality"],
      "common_user_problems": ["over-sharpening", "color distortion", "no improvement for very low quality"],
      "tool_intro_messages_en": ["Turn blurry photos crystal clear! ✨", "Make your images HD quality in 1 click!"],
      "tool_intro_messages_hi": ["धुंधली फोटो को क्रिस्टल क्लियर बनाएं! ✨", "1 क्लिक में इमेज को HD क्वालिटी बनाएं!"],
      "success_messages_en": ["Image enhanced! Looks much sharper now 🎉", "Done! Download your improved image below ✨"],
      "success_messages_hi": ["इमेज एन्हांस हो गई! अब बहुत शार्पर लग रही है 🎉", "हो गया! बेहतर इमेज नीचे डाउनलोड करें ✨"],
      "error_messages_en": ["Enhancement failed. Try a smaller image or different format.", "Image too blurry to enhance. Try a clearer original."],
      "error_messages_hi": ["एन्हांसमेंट फेल हुआ। छोटी इमेज या दूसरे फॉर्मेट में आज़माएं।", "इमेज बहुत धुंधली है। साफ ओरिजिनल आज़माएं।"],
      "fallback_messages_en": ["Enhancer not working? Try Upscale tool instead! 🔍", "Some images need manual editing. Try our BG Remover first."],
      "fallback_messages_hi": ["एन्हांसर काम नहीं कर रहा? अपस्केल टूल आज़माएं! 🔍", "कुछ इमेज को मैन्युअल एडिटिंग की जरूरत होती है। पहले BG रिमूवर आज़माएं।"],
      "related_tools": ["bg-remover", "image-upscale"],
      "alternative_tools": ["image-upscale", "compressor"],
      "recommended_tools": ["bg-remover", "face-swap"],
      "user_guidance_en": ["Upload any JPG/PNG", "AI will denoise and sharpen", "Download enhanced version"],
      "user_guidance_hi": ["कोई भी JPG/PNG अपलोड करें", "AI denoise और sharpen करेगा", "एन्हांस्ड वर्जन डाउनलोड करें"],
      "engagement_messages_en": ["Best for old family photos! 📸", "Used by 50k+ creators worldwide 🌍"],
      "engagement_messages_hi": ["पुरानी फैमिली फोटो के लिए बेस्ट! 📸", "दुनिया भर में 50k+ क्रिएटर्स द्वारा उपयोग किया गया 🌍"]
    },
    {
      "tool_name": "Image Compressor",
      "slug": "compressor",
      "url": "https://www.texlyonline.in/tools/compressor",
      "category": "image-tools",
      "description_en": "Reduce image file size without quality loss",
      "description_hi": "गुणवत्ता खोए बिना इमेज का साइज़ कम करें",
      "keywords": ["compress image", "reduce image size", "image compressor", "smaller image file", "इमेज कंप्रेसर"],
      "search_terms": ["make image smaller", "reduce mb", "compress jpg", "optimize image for web"],
      "common_user_problems": ["too much compression ruins quality", "large original files", "format not supported"],
      "tool_intro_messages_en": ["Shrink your images by up to 80%! 📦", "Perfect for website uploads and emails!"],
      "tool_intro_messages_hi": ["अपनी इमेज 80% तक छोटी करें! 📦", "वेबसाइट अपलोड और ईमेल के लिए परफेक्ट!"],
      "success_messages_en": ["Image compressed! Saved XX% space 🎉", "Done! Your smaller image is ready below ✨"],
      "success_messages_hi": ["इमेज कंप्रेस हो गई! XX% स्पेस बचा 🎉", "हो गया! आपकी छोटी इमेज नीचे तैयार है ✨"],
      "error_messages_en": ["Compression failed. Try a different image format.", "File is already very small."],
      "error_messages_hi": ["कंप्रेशन फेल हुआ। दूसरे इमेज फॉर्मेट में आज़माएं।", "फाइल पहले से ही बहुत छोटी है।"],
      "fallback_messages_en": ["Compressor stuck? Try resizing your image first using another tool.", "For PNG files, try converting to JPG first."],
      "fallback_messages_hi": ["कंप्रेसर अटक गया? पहले किसी अन्य टूल से इमेज का साइज़ बदलें।", "PNG फाइलों के लिए, पहले JPG में बदलने का प्रयास करें।"],
      "related_tools": ["image-upscale", "enhancer"],
      "alternative_tools": ["image-upscale", "bg-remover"],
      "recommended_tools": ["pdf-compressor", "image-to-pdf-converter"],
      "user_guidance_en": ["Upload JPG/PNG (max 10MB)", "Choose compression level", "Download optimized image"],
      "user_guidance_hi": ["JPG/PNG अपलोड करें (अधिकतम 10MB)", "कंप्रेशन लेवल चुनें", "ऑप्टिमाइज़्ड इमेज डाउनलोड करें"],
      "engagement_messages_en": ["Faster websites = happier visitors! 🚀", "Save disk space and upload time!"],
      "engagement_messages_hi": ["तेज़ वेबसाइट = खुश विज़िटर! 🚀", "डिस्क स्पेस और अपलोड टाइम बचाएं!"]
    },
    {
      "tool_name": "Image Upscale",
      "slug": "image-upscale",
      "url": "https://www.texlyonline.in/tools/image-upscale",
      "category": "image-tools",
      "description_en": "Increase image resolution with AI (2x, 4x)",
      "description_hi": "AI से इमेज रेज़ोल्यूशन बढ़ाएं (2x, 4x)",
      "keywords": ["upscale image", "increase resolution", "enlarge image", "image upscaler", "इमेज अपस्केल"],
      "search_terms": ["make image bigger", "increase pixel size", "enhance resolution", "blow up image without losing quality"],
      "common_user_problems": ["artifacts appear", "faces distorted", "very slow for large images"],
      "tool_intro_messages_en": ["Make small images big and sharp! 📈", "Perfect for printing or social media!"],
      "tool_intro_messages_hi": ["छोटी इमेज को बड़ी और शार्प बनाएं! 📈", "प्रिंटिंग या सोशल मीडिया के लिए परफेक्ट!"],
      "success_messages_en": ["Image upscaled 2x! Download your HD version 🎉", "Your image is now 4x larger and crystal clear! ✨"],
      "success_messages_hi": ["इमेज 2x अपस्केल हो गई! अपना HD वर्जन डाउनलोड करें 🎉", "आपकी इमेज अब 4x बड़ी और क्रिस्टल क्लियर है! ✨"],
      "error_messages_en": ["Upscaling failed. Try a smaller image or lower scaling factor.", "Image too large. Max 2MB for 4x upscale."],
      "error_messages_hi": ["अपस्केलिंग फेल हुई। छोटी इमेज या कम स्केलिंग फैक्टर आज़माएं।", "इमेज बहुत बड़ी है। 4x अपस्केल के लिए अधिकतम 2MB।"],
      "fallback_messages_en": ["Upscale not working? Try Image Enhancer first to improve quality!", "For very small images, try our AI Image Generator instead."],
      "fallback_messages_hi": ["अपस्केल काम नहीं कर रहा? पहले इमेज एन्हांसर से क्वालिटी सुधारें!", "बहुत छोटी इमेज के लिए, इसके बजाय हमारा AI इमेज जेनरेटर आज़माएं।"],
      "related_tools": ["enhancer", "compressor"],
      "alternative_tools": ["enhancer", "face-swap"],
      "recommended_tools": ["bg-remover", "enhancer"],
      "user_guidance_en": ["Upload JPG/PNG (max 2MB)", "Select 2x or 4x upscale", "Download the enlarged version"],
      "user_guidance_hi": ["JPG/PNG अपलोड करें (अधिकतम 2MB)", "2x या 4x अपस्केल चुनें", "बड़ा वर्जन डाउनलोड करें"],
      "engagement_messages_en": ["From thumbnail to poster size! 🖼️", "Great for old photos and screenshots!"],
      "engagement_messages_hi": ["थंबनेल से पोस्टर साइज़ तक! 🖼️", "पुरानी तस्वीरों और स्क्रीनशॉट के लिए बढ़िया!"]
    },
    {
      "tool_name": "WhatsApp Text Formatter",
      "slug": "whatsapp-text-formatter",
      "url": "https://www.texlyonline.in/tool/whatsapp-text-formatter",
      "category": "text-tools",
      "description_en": "Format text for WhatsApp (bold, italic, strikethrough, monospace)",
      "description_hi": "WhatsApp के लिए टेक्स्ट फॉर्मेट करें (बोल्ड, इटैलिक, स्ट्राइक, मोनोस्पेस)",
      "keywords": ["whatsapp formatting", "bold text whatsapp", "italic whatsapp", "strikethrough whatsapp", "monospace whatsapp", "व्हाट्सएप टेक्स्ट फॉर्मेट"],
      "search_terms": ["how to bold in whatsapp", "whatsapp text tricks", "format whatsapp message"],
      "common_user_problems": ["forget syntax", "want quick copy-paste", "need to format long messages"],
      "tool_intro_messages_en": ["Make your WhatsApp messages stand out! ✨", "Bold, italic, strikethrough - all in one click!"],
      "tool_intro_messages_hi": ["अपने WhatsApp संदेशों को खास बनाएं! ✨", "बोल्ड, इटैलिक, स्ट्राइक - सब एक क्लिक में!"],
      "success_messages_en": ["Text formatted! Copy and paste into WhatsApp now 📱", "Your message is ready to impress! 🎉"],
      "success_messages_hi": ["टेक्स्ट फॉर्मेट हो गया! अब WhatsApp में कॉपी-पेस्ट करें 📱", "आपका संदेश इम्प्रेस करने के लिए तैयार है! 🎉"],
      "error_messages_en": ["No text entered. Write something first!", "Formatting failed. Try simpler text."],
      "error_messages_hi": ["कोई टेक्स्ट नहीं दर्ज किया गया। पहले कुछ लिखें!", "फॉर्मेटिंग फेल हुई। सरल टेक्स्ट आज़माएं।"],
      "fallback_messages_en": ["WhatsApp formatter glitching? Try our Text Case Converter instead!", "For fancy fonts, check out Fancy Text Generator."],
      "fallback_messages_hi": ["WhatsApp फॉर्मेटर गड़बड़ कर रहा है? इसके बजाय टेक्स्ट केस कन्वर्टर आज़माएं!", "फैंसी फोंट के लिए, फैंसी टेक्स्ट जेनरेटर देखें।"],
      "related_tools": ["fancy-text-generator", "case-converters"],
      "alternative_tools": ["fancy-text-generator", "upper-case-converter"],
      "recommended_tools": ["text-repeater-tool", "character-counter-tool"],
      "user_guidance_en": ["Type or paste your message", "Click formatting buttons", "Copy and send on WhatsApp!"],
      "user_guidance_hi": ["अपना संदेश टाइप या पेस्ट करें", "फॉर्मेटिंग बटन पर क्लिक करें", "कॉपी करें और WhatsApp पर भेजें!"],
      "engagement_messages_en": ["Pro tip: Combine formats like *bold* and _italic_ together!", "Make your status updates go viral!"],
      "engagement_messages_hi": ["प्रो टिप: *bold* और _italic_ जैसे फॉर्मेट को एक साथ मिलाएं!", "अपने स्टेटस अपडेट को वायरल बनाएं!"]
    },
    {
      "tool_name": "Number to Words Converter",
      "slug": "number-to-words-converter",
      "url": "https://www.texlyonline.in/tool/number-to-words-converter",
      "category": "converter-tools",
      "description_en": "Convert numbers to English words (e.g., 123 → one hundred twenty-three)",
      "description_hi": "नंबर को शब्दों में बदलें (जैसे, 123 → एक सौ तेईस)",
      "keywords": ["number to words", "spell number", "convert number to text", "number spelling", "नंबर टू वर्ड्स"],
      "search_terms": ["how to write number in words", "spell number", "number to english words", "convert currency to words"],
      "common_user_problems": ["cheque writing", "invoice generation", "legal documents need spelling"],
      "tool_intro_messages_en": ["Write numbers as words for cheques and invoices! 💰", "Never misspell a number again!"],
      "tool_intro_messages_hi": ["चेक और इनवॉइस के लिए नंबर को शब्दों में लिखें! 💰", "फिर कभी नंबर की स्पेलिंग गलत न करें!"],
      "success_messages_en": ["Converted! Your number is now in words 🎉", "Perfect for your document! Copy it below ✨"],
      "success_messages_hi": ["बदल दिया गया! आपका नंबर अब शब्दों में है 🎉", "आपके दस्तावेज़ के लिए एकदम सही! इसे नीचे कॉपी करें ✨"],
      "error_messages_en": ["Enter a valid number (0 to 999,999,999).", "Too large! Max 9 digits supported."],
      "error_messages_hi": ["एक मान्य संख्या दर्ज करें (0 से 999,999,999 तक)।", "बहुत बड़ा! अधिकतम 9 अंक समर्थित हैं।"],
      "fallback_messages_en": ["Number converter stuck? Try our Word Counter tool instead!", "Need to convert currency? Use this tool and add 'dollars/rupees' manually."],
      "fallback_messages_hi": ["नंबर कन्वर्टर अटक गया? इसके बजाय वर्ड काउंटर टूल आज़माएं!", "करेंसी कन्वर्ट करनी है? इस टूल का उपयोग करें और मैन्युअल रूप से 'रुपए/डॉलर' जोड़ें।"],
      "related_tools": ["word-counter-tool", "character-counter-tool"],
      "alternative_tools": ["word-counter-tool", "reading-time-calculator"],
      "recommended_tools": ["find-and-replace-text", "text-to-list-converter"],
      "user_guidance_en": ["Type a number (e.g., 1234)", "Click Convert", "Copy the spelled-out words"],
      "user_guidance_hi": ["एक नंबर टाइप करें (जैसे, 1234)", "Convert पर क्लिक करें", "शब्दों को कॉपी करें"],
      "engagement_messages_en": ["Perfect for writing bank cheques! 🏦", "Teachers love this for worksheets! 📚"],
      "engagement_messages_hi": ["बैंक चेक लिखने के लिए एकदम सही! 🏦", "शिक्षकों को यह वर्कशीट के लिए पसंद है! 📚"]
    },
    {
      "tool_name": "PDF Editor",
      "slug": "pdf-editor-online",
      "url": "https://www.texlyonline.in/tool/pdf-editor-online",
      "category": "pdf-tools",
      "description_en": "Edit PDF files online (text, images, annotations)",
      "description_hi": "PDF फाइलों को ऑनलाइन एडिट करें (टेक्स्ट, इमेज, एनोटेशन)",
      "keywords": ["pdf editor", "edit pdf", "modify pdf", "pdf annotation", "pdf online editor", "पीडीएफ एडिटर"],
      "search_terms": ["change text in pdf", "edit pdf online free", "add text to pdf", "pdf editor no signup"],
      "common_user_problems": ["can't edit scanned PDFs", "free tier limitations", "watermark on output"],
      "tool_intro_messages_en": ["Edit PDFs like Word documents! ✍️", "Add text, highlight, or draw on any PDF!"],
      "tool_intro_messages_hi": ["PDF को Word दस्तावेज़ों की तरह एडिट करें! ✍️", "किसी भी PDF पर टेक्स्ट जोड़ें, हाइलाइट करें या ड्रा करें!"],
      "success_messages_en": ["PDF edited successfully! Download your file 🎉", "All changes saved! Your PDF is ready ✨"],
      "success_messages_hi": ["PDF सफलतापूर्वक एडिट हो गई! अपनी फाइल डाउनलोड करें 🎉", "सभी परिवर्तन सहेजे गए! आपकी PDF तैयार है ✨"],
      "error_messages_en": ["Upload failed. PDF might be corrupted or password protected.", "Editing failed. Try a smaller file."],
      "error_messages_hi": ["अपलोड विफल हुआ। PDF क्षतिग्रस्त या पासवर्ड संरक्षित हो सकती है।", "एडिटिंग विफल हुई। छोटी फाइल आज़माएं।"],
      "fallback_messages_en": ["PDF Editor not working? Try Merge PDF or Split PDF instead!", "For scanned PDFs, try converting to Word first."],
      "fallback_messages_hi": ["PDF एडिटर काम नहीं कर रहा? इसके बजाय PDF मर्ज या स्प्लिट आज़माएं!", "स्कैन की गई PDF के लिए, पहले Word में बदलने का प्रयास करें।"],
      "related_tools": ["pdf-to-word-converter", "merge-pdf", "split-pdf"],
      "alternative_tools": ["pdf-to-word-converter", "pdf-compressor"],
      "recommended_tools": ["word-to-pdf-converter", "image-to-pdf-converter"],
      "user_guidance_en": ["Upload your PDF file", "Use toolbar to edit text/images", "Save and download"],
      "user_guidance_hi": ["अपनी PDF फाइल अपलोड करें", "टेक्स्ट/इमेज एडिट करने के लिए टूलबार का उपयोग करें", "सेव करें और डाउनलोड करें"],
      "engagement_messages_en": ["No need to buy expensive software! 💸", "Fill forms, sign docs, all online!"],
      "engagement_messages_hi": ["महंगा सॉफ्टवेयर खरीदने की जरूरत नहीं! 💸", "फॉर्म भरें, दस्तावेज़ों पर हस्ताक्षर करें, सब ऑनलाइन!"]
    },
    {
      "tool_name": "Image to PDF Converter",
      "slug": "image-to-pdf-converter",
      "url": "https://www.texlyonline.in/tool/image-to-pdf-converter",
      "category": "pdf-tools",
      "description_en": "Convert images (JPG, PNG) to PDF",
      "description_hi": "इमेज (JPG, PNG) को PDF में बदलें",
      "keywords": ["image to pdf", "jpg to pdf", "png to pdf", "convert image to pdf", "इमेज टू पीडीएफ"],
      "search_terms": ["make pdf from images", "convert photo to pdf", "multiple images to one pdf", "jpeg to pdf converter"],
      "common_user_problems": ["images not in order", "want one PDF per image", "large file size"],
      "tool_intro_messages_en": ["Turn your photos into a PDF document! 📸→📄", "Combine multiple images into one PDF!"],
      "tool_intro_messages_hi": ["अपनी तस्वीरों को PDF दस्तावेज़ में बदलें! 📸→📄", "कई इमेज को एक PDF में बदलें!"],
      "success_messages_en": ["PDF created from your images! 🎉", "Done! Download your new PDF below ✨"],
      "success_messages_hi": ["आपकी इमेज से PDF बन गई! 🎉", "हो गया! अपनी नई PDF नीचे डाउनलोड करें ✨"],
      "error_messages_en": ["Conversion failed. Check image format or size.", "Too many images. Max 20 images per session."],
      "error_messages_hi": ["रूपांतरण विफल रहा। इमेज फॉर्मेट या साइज़ जांचें।", "बहुत सारी इमेज। प्रति सत्र अधिकतम 20 इमेज।"],
      "fallback_messages_en": ["Converter stuck? Try PDF to Image converter for reverse!", "For large images, compress them first."],
      "fallback_messages_hi": ["कन्वर्टर अटक गया? रिवर्स के लिए PDF टू इमेज कन्वर्टर आज़माएं!", "बड़ी इमेज के लिए, पहले उन्हें कंप्रेस करें।"],
      "related_tools": ["pdf-to-image-converter", "image-compressor"],
      "alternative_tools": ["pdf-to-image-converter", "word-to-pdf-converter"],
      "recommended_tools": ["merge-pdf", "pdf-compressor"],
      "user_guidance_en": ["Upload images (JPG, PNG)", "Arrange order if multiple", "Click Convert and download PDF"],
      "user_guidance_hi": ["इमेज अपलोड करें (JPG, PNG)", "कई हों तो क्रम व्यवस्थित करें", "Convert पर क्लिक करें और PDF डाउनलोड करें"],
      "engagement_messages_en": ["Perfect for creating photo albums! 📚", "Great for sending scanned documents!"],
      "engagement_messages_hi": ["फोटो एलबम बनाने के लिए एकदम सही! 📚", "स्कैन किए गए दस्तावेज़ भेजने के लिए बढ़िया!"]
    },
    {
      "tool_name": "PDF Compressor",
      "slug": "compress-pdf-online",
      "url": "https://www.texlyonline.in/tool/compress-pdf-online",
      "category": "pdf-tools",
      "description_en": "Reduce PDF file size",
      "description_hi": "PDF फाइल का साइज़ कम करें",
      "keywords": ["compress pdf", "reduce pdf size", "pdf compressor", "smaller pdf", "पीडीएफ कंप्रेसर"],
      "search_terms": ["make pdf smaller", "shrink pdf file", "pdf size reducer", "optimize pdf"],
      "common_user_problems": ["quality loss after compression", "text becomes blurry", "image quality degrades"],
      "tool_intro_messages_en": ["Shrink your PDFs for email! 📧", "Up to 90% size reduction possible!"],
      "tool_intro_messages_hi": ["ईमेल के लिए अपनी PDF छोटी करें! 📧", "90% तक साइज़ कमी संभव है!"],
      "success_messages_en": ["PDF compressed! Saved XX MB 🎉", "Your smaller PDF is ready to download ✨"],
      "success_messages_hi": ["PDF कंप्रेस हो गई! XX MB बचा 🎉", "आपकी छोटी PDF डाउनलोड करने के लिए तैयार है ✨"],
      "error_messages_en": ["Compression failed. PDF might be corrupted.", "File already optimized. No further compression possible."],
      "error_messages_hi": ["कंप्रेशन विफल हुआ। PDF क्षतिग्रस्त हो सकती है।", "फाइल पहले से अनुकूलित है। आगे कोई कंप्रेशन संभव नहीं है।"],
      "fallback_messages_en": ["PDF Compressor stuck? Try our Image Compressor for images inside PDF!", "For large PDFs, try splitting first."],
      "fallback_messages_hi": ["PDF कंप्रेसर अटक गया? PDF के अंदर की इमेज के लिए हमारा इमेज कंप्रेसर आज़माएं!", "बड़ी PDF के लिए, पहले स्प्लिट करने का प्रयास करें।"],
      "related_tools": ["image-compressor", "merge-pdf"],
      "alternative_tools": ["image-compressor", "pdf-editor"],
      "recommended_tools": ["split-pdf", "pdf-to-word-converter"],
      "user_guidance_en": ["Upload PDF (max 20MB)", "Choose compression level", "Download optimized PDF"],
      "user_guidance_hi": ["PDF अपलोड करें (अधिकतम 20MB)", "कंप्रेशन लेवल चुनें", "ऑप्टिमाइज़्ड PDF डाउनलोड करें"],
      "engagement_messages_en": ["Faster uploads, less storage! 💾", "Perfect for Gmail attachments (25MB limit)!"],
      "engagement_messages_hi": ["तेज़ अपलोड, कम स्टोरेज! 💾", "जीमेल अटैचमेंट (25MB सीमा) के लिए एकदम सही!"]
    },
    {
      "tool_name": "Remove Extra Spaces",
      "slug": "remove-extra-spaces-online",
      "url": "https://www.texlyonline.in/tool/remove-extra-spaces-online",
      "category": "text-tools",
      "description_en": "Remove extra spaces, tabs, and line breaks from text",
      "description_hi": "टेक्स्ट से एक्स्ट्रा स्पेस, टैब और लाइन ब्रेक हटाएं",
      "keywords": ["remove extra spaces", "delete spaces", "clean text", "remove white spaces", "space remover", "एक्स्ट्रा स्पेस हटाएं"],
      "search_terms": ["remove double spaces", "clean up text spacing", "delete extra spaces online", "fix spacing in text"],
      "common_user_problems": ["copied text has weird spacing", "too many spaces between words", "random line breaks"],
      "tool_intro_messages_en": ["Clean messy text in 1 click! 🧹", "Remove double spaces, tabs, and extra line breaks!"],
      "tool_intro_messages_hi": ["1 क्लिक में गंदे टेक्स्ट को साफ करें! 🧹", "डबल स्पेस, टैब और एक्स्ट्रा लाइन ब्रेक हटाएं!"],
      "success_messages_en": ["Text cleaned! All extra spaces removed 🎉", "Perfectly formatted text is ready!"],
      "success_messages_hi": ["टेक्स्ट साफ हो गया! सभी एक्स्ट्रा स्पेस हटा दिए गए 🎉", "बिल्कुल सही फॉर्मेट वाला टेक्स्ट तैयार है!"],
      "error_messages_en": ["No text entered. Paste something first.", "Text too long. Max 100,000 characters."],
      "error_messages_hi": ["कोई टेक्स्ट नहीं दर्ज किया गया। पहले कुछ पेस्ट करें।", "टेक्स्ट बहुत लंबा है। अधिकतम 100,000 अक्षर।"],
      "fallback_messages_en": ["Spaces remover glitching? Try Remove Line Breaks tool!", "For HTML cleanup, try our Remove HTML Tags tool."],
      "fallback_messages_hi": ["स्पेस रिमूवर गड़बड़ कर रहा है? लाइन ब्रेक रिमूव टूल आज़माएं!", "HTML सफाई के लिए, हमारा HTML टैग रिमूव टूल आज़माएं।"],
      "related_tools": ["remove-line-breaks", "remove-duplicate-lines", "clean-text"],
      "alternative_tools": ["remove-line-breaks", "remove-extra-spaces"],
      "recommended_tools": ["word-counter-tool", "character-counter-tool"],
      "user_guidance_en": ["Paste your text", "Click 'Remove Spaces'", "Copy cleaned text"],
      "user_guidance_hi": ["अपना टेक्स्ट पेस्ट करें", "'Remove Spaces' पर क्लिक करें", "साफ किया हुआ टेक्स्ट कॉपी करें"],
      "engagement_messages_en": ["Clean text = professional look! 💼", "Great for SEO content and blog posts!"],
      "engagement_messages_hi": ["साफ टेक्स्ट = पेशेवर लुक! 💼", "एसईओ सामग्री और ब्लॉग पोस्ट के लिए बढ़िया!"]
    },
    {
      "tool_name": "Remove Line Breaks",
      "slug": "remove-line-breaks-tool",
      "url": "https://www.texlyonline.in/tool/remove-line-breaks-tool",
      "category": "text-tools",
      "description_en": "Remove line breaks and join text into a single paragraph",
      "description_hi": "लाइन ब्रेक हटाएं और टेक्स्ट को एक पैराग्राफ में जोड़ें",
      "keywords": ["remove line breaks", "join lines", "remove newlines", "line break remover", "लाइन ब्रेक हटाएं"],
      "search_terms": ["remove enter key text", "join text lines", "remove line breaks online"],
      "common_user_problems": ["copied PDF text has line breaks", "want continuous text", "remove extra enters"],
      "tool_intro_messages_en": ["Join broken lines into smooth paragraphs! 📝", "Perfect for cleaning copied PDF text!"],
      "tool_intro_messages_hi": ["टूटी हुई लाइनों को स्मूद पैराग्राफ में जोड़ें! 📝", "कॉपी की गई PDF टेक्स्ट को साफ करने के लिए एकदम सही!"],
      "success_messages_en": ["Line breaks removed! Text is now continuous 🎉", "Done! Your text is now one clean paragraph ✨"],
      "success_messages_hi": ["लाइन ब्रेक हटा दिए गए! टेक्स्ट अब निरंतर है 🎉", "हो गया! आपका टेक्स्ट अब एक साफ पैराग्राफ है ✨"],
      "error_messages_en": ["No text entered. Paste content first.", "Text too large. Max 50,000 characters."],
      "error_messages_hi": ["कोई टेक्स्ट नहीं दर्ज किया गया। पहले कंटेंट पेस्ट करें।", "टेक्स्ट बहुत बड़ा है। अधिकतम 50,000 अक्षर।"],
      "fallback_messages_en": ["Line break remover stuck? Try Remove Extra Spaces tool first!", "For advanced cleanup, use our Text Cleaner tool."],
      "fallback_messages_hi": ["लाइन ब्रेक रिमूवर अटक गया? पहले एक्स्ट्रा स्पेस रिमूव टूल आज़माएं!", "उन्नत सफाई के लिए, हमारे टेक्स्ट क्लीनर टूल का उपयोग करें।"],
      "related_tools": ["remove-extra-spaces", "clean-text", "remove-duplicate-lines"],
      "alternative_tools": ["remove-extra-spaces", "clean-text"],
      "recommended_tools": ["word-counter-tool", "reading-time-calculator"],
      "user_guidance_en": ["Paste text with line breaks", "Click 'Remove Line Breaks'", "Copy continuous text"],
      "user_guidance_hi": ["लाइन ब्रेक वाला टेक्स्ट पेस्ट करें", "'Remove Line Breaks' पर क्लिक करें", "निरंतर टेक्स्ट कॉपी करें"],
      "engagement_messages_en": ["Fix messy PDF copies in seconds! ⏱️", "Writers love this tool! ✍️"],
      "engagement_messages_hi": ["गंदी PDF कॉपी को सेकंडों में ठीक करें! ⏱️", "लेखकों को यह टूल पसंद है! ✍️"]
    },
    {
      "tool_name": "Word Counter",
      "slug": "word-counter-online-free",
      "url": "https://www.texlyonline.in/tool/word-counter-online-free",
      "category": "text-tools",
      "description_en": "Count words, characters, sentences, and paragraphs",
      "description_hi": "शब्द, अक्षर, वाक्य और पैराग्राफ गिनें",
      "keywords": ["word counter", "count words", "character counter", "word count tool", "शब्द गणक", "वर्ड काउंटर"],
      "search_terms": ["how many words", "count characters in text", "word count online", "check word count"],
      "common_user_problems": ["need quick stats", "essay word limit", "social media character limit"],
      "tool_intro_messages_en": ["Know exactly how many words you've written! 📊", "Perfect for essays, tweets, and SEO!"],
      "tool_intro_messages_hi": ["जानें वास्तव में आपने कितने शब्द लिखे हैं! 📊", "निबंध, ट्वीट और SEO के लिए एकदम सही!"],
      "success_messages_en": ["Counted! Words: X, Characters: Y 🎉", "Your text stats are ready! See the full breakdown ✨"],
      "success_messages_hi": ["गिनती हो गई! शब्द: X, अक्षर: Y 🎉", "आपके टेक्स्ट के आंकड़े तैयार हैं! पूरा विवरण देखें ✨"],
      "error_messages_en": ["No text entered. Type or paste something.", "Text too large. Try splitting into smaller parts."],
      "error_messages_hi": ["कोई टेक्स्ट नहीं दर्ज किया गया। कुछ टाइप या पेस्ट करें।", "टेक्स्ट बहुत बड़ा है। छोटे भागों में विभाजित करने का प्रयास करें।"],
      "fallback_messages_en": ["Word counter slow? Try our Character Counter for faster results!", "Need reading time? Check our Reading Time Calculator!"],
      "fallback_messages_hi": ["वर्ड काउंटर धीमा है? तेज़ परिणामों के लिए कैरेक्टर काउंटर आज़माएं!", "रीडिंग टाइम चाहिए? हमारा रीडिंग टाइम कैलकुलेटर देखें!"],
      "related_tools": ["character-counter-tool", "reading-time-calculator", "sentence-counter"],
      "alternative_tools": ["character-counter-tool", "reading-time-calculator"],
      "recommended_tools": ["remove-extra-spaces", "remove-line-breaks"],
      "user_guidance_en": ["Type or paste your text", "Instant stats update as you type", "Use for essays, tweets, blogs"],
      "user_guidance_hi": ["अपना टेक्स्ट टाइप या पेस्ट करें", "टाइप करते ही इंस्टेंट आंकड़े अपडेट होते हैं", "निबंध, ट्वीट, ब्लॉग के लिए उपयोग करें"],
      "engagement_messages_en": ["300 words per minute average reading speed! 🚀", "Perfect for students and writers!"],
      "engagement_messages_hi": ["औसत पढ़ने की गति 300 शब्द प्रति मिनट! 🚀", "छात्रों और लेखकों के लिए एकदम सही!"]
    },
    {
      "tool_name": "Upside Down Text Generator",
      "slug": "upside-down-text-generator",
      "url": "https://www.texlyonline.in/tool/upside-down-text-generator",
      "category": "text-tools",
      "description_en": "Flip text upside down (ʇxǝʇ uʍop ǝpısdn)",
      "description_hi": "टेक्स्ट को उल्टा करें (ʇxǝʇ uʍop ǝpısdn)",
      "keywords": ["upside down text", "flip text", "reverse text", "text flipper", "उल्टा टेक्स्ट", "फ्लिप टेक्स्ट"],
      "search_terms": ["generate upside down text", "text upside down converter", "funny text generator"],
      "common_user_problems": ["just want fun text", "social media bio", "cool usernames"],
      "tool_intro_messages_en": ["Turn your text upside down for fun! 🙃", "Make your friends confused with this!"],
      "tool_intro_messages_hi": ["मज़े के लिए अपने टेक्स्ट को उल्टा करें! 🙃", "इससे अपने दोस्तों को कन्फ्यूज करें!"],
      "success_messages_en": ["Text flipped upside down! Copy and share 🙃", "Here's your upside down text! Looks funny! 🎉"],
      "success_messages_hi": ["टेक्स्ट उल्टा हो गया! कॉपी करें और साझा करें 🙃", "यह रहा आपका उल्टा टेक्स्ट! मज़ेदार लग रहा है! 🎉"],
      "error_messages_en": ["No text entered. Write something first!", "Some characters can't be flipped."],
      "error_messages_hi": ["कोई टेक्स्ट नहीं दर्ज किया गया। पहले कुछ लिखें!", "कुछ अक्षर नहीं पलट सकते।"],
      "fallback_messages_en": ["Text flipper not working? Try our Mirror Text Generator!", "For fancy fonts, use Fancy Text Generator."],
      "fallback_messages_hi": ["टेक्स्ट फ्लिपर काम नहीं कर रहा? मिरर टेक्स्ट जेनरेटर आज़माएं!", "फैंसी फोंट के लिए, फैंसी टेक्स्ट जेनरेटर का उपयोग करें।"],
      "related_tools": ["mirror-text-generator", "fancy-text-generator", "text-reverser"],
      "alternative_tools": ["mirror-text-generator", "text-reverser"],
      "recommended_tools": ["fancy-text-generator", "zalgo-text-generator"],
      "user_guidance_en": ["Type normal text", "Click 'Flip'", "Copy upside down text"],
      "user_guidance_hi": ["सामान्य टेक्स्ट टाइप करें", "'Flip' पर क्लिक करें", "उल्टा टेक्स्ट कॉपी करें"],
      "engagement_messages_en": ["Great for pranking your friends! 🤪", "Use in Instagram bios for attention!"],
      "engagement_messages_hi": ["अपने दोस्तों को प्रैंक करने के लिए बढ़िया! 🤪", "ध्यान आकर्षित करने के लिए इंस्टाग्राम बायो में उपयोग करें!"]
    },
    {
      "tool_name": "QR Code Generator",
      "slug": "qr-code-generator-online",
      "url": "https://www.texlyonline.in/tools/qr-code-generator-online",
      "category": "utility-tools",
      "description_en": "Generate QR codes for URLs, text, contacts, WiFi",
      "description_hi": "URL, टेक्स्ट, संपर्क, WiFi के लिए QR कोड बनाएं",
      "keywords": ["qr code generator", "create qr code", "qr maker", "qr code", "क्यूआर कोड जेनरेटर"],
      "search_terms": ["make qr code", "generate qr code free", "qr code for link", "download qr code image"],
      "common_user_problems": ["code not scanning", "low resolution", "can't customize colors"],
      "tool_intro_messages_en": ["Turn any link into a QR code! 📱", "Share WiFi passwords, contacts, and more!"],
      "tool_intro_messages_hi": ["किसी भी लिंक को QR कोड में बदलें! 📱", "WiFi पासवर्ड, संपर्क और बहुत कुछ साझा करें!"],
      "success_messages_en": ["QR Code generated! Download and share 🎉", "Your QR code is ready to scan! ✨"],
      "success_messages_hi": ["QR कोड जेनरेट हो गया! डाउनलोड करें और साझा करें 🎉", "आपका QR कोड स्कैन करने के लिए तैयार है! ✨"],
      "error_messages_en": ["Enter valid URL or text first.", "Content too long for QR code. Try shorter text."],
      "error_messages_hi": ["पहले मान्य URL या टेक्स्ट दर्ज करें।", "कंटेंट QR कोड के लिए बहुत लंबा है। छोटा टेक्स्ट आज़माएं।"],
      "fallback_messages_en": ["QR generator stuck? Try simplifying your text.", "Need high resolution? Download as PNG or SVG."],
      "fallback_messages_hi": ["QR जेनरेटर अटक गया? अपने टेक्स्ट को सरल बनाने का प्रयास करें।", "उच्च रिज़ॉल्यूशन चाहिए? PNG या SVG के रूप में डाउनलोड करें।"],
      "related_tools": ["color-palette-generator", "image-generator"],
      "alternative_tools": ["color-palette-generator", "fancy-text-generator"],
      "recommended_tools": ["image-to-pdf-converter", "compressor"],
      "user_guidance_en": ["Enter URL, text, or WiFi details", "Click Generate", "Download PNG or SVG"],
      "user_guidance_hi": ["URL, टेक्स्ट या WiFi विवरण दर्ज करें", "Generate पर क्लिक करें", "PNG या SVG डाउनलोड करें"],
      "engagement_messages_en": ["Used by businesses for contactless menus! 🍽️", "Create QR codes for your business cards!"],
      "engagement_messages_hi": ["कॉन्टैक्टलेस मेनू के लिए व्यवसायों द्वारा उपयोग किया जाता है! 🍽️", "अपने बिजनेस कार्ड के लिए QR कोड बनाएं!"]
    }
  ],
  "recommendation_engine": {
    "rules": [
      { "if_tool_category": "image-tools", "recommend": ["compressor", "enhancer", "bg-remover"] },
      { "if_tool_category": "pdf-tools", "recommend": ["pdf-compressor", "pdf-to-word-converter", "merge-pdf"] },
      { "if_tool_category": "text-tools", "recommend": ["word-counter-tool", "remove-extra-spaces", "case-converters"] },
      { "if_task": "make image smaller", "recommend": ["compressor", "image-upscale"] },
      { "if_task": "edit pdf", "recommend": ["pdf-editor", "pdf-to-word-converter", "merge-pdf"] },
      { "if_task": "clean text", "recommend": ["remove-extra-spaces", "remove-line-breaks", "remove-special-characters"] },
      { "if_task": "count words", "recommend": ["word-counter-tool", "character-counter-tool", "reading-time-calculator"] },
      { "if_task": "background remove", "recommend": ["bg-remover", "enhancer", "face-swap"] }
    ]
  },
  "fallback_system": {
    "global_fallback_messages_en": ["That tool might be busy. Try one of these instead:", "Hmm, facing some issues. Here are similar tools:"],
    "global_fallback_messages_hi": ["हो सकता है कि वह टूल व्यस्त हो। इसके बजाय इनमें से एक आज़माएं:", "हम्म, कुछ समस्याएं आ रही हैं। यहां समान टूल हैं:"],
    "fallback_tools_by_category": {
      "image": ["bg-remover", "enhancer", "compressor"],
      "pdf": ["pdf-compressor", "pdf-to-word-converter", "merge-pdf"],
      "text": ["word-counter-tool", "remove-extra-spaces", "case-converters"]
    }
  },
  "engagement_system": {
    "user_activity_messages_en": [
      { "after_success": "Great job! Want to try a related tool?", "action": "show_recommendations" },
      { "after_3_tools": "You're on fire! Try our AI Face Swap for fun! 🔥", "action": "recommend_face_swap" },
      { "idle_30_seconds": "Stuck? Need help? Ask me anything about Texly tools! 💬", "action": "show_help" }
    ],
    "user_activity_messages_hi": [
      { "after_success": "बहुत बढ़िया! कोई संबंधित टूल आज़माना चाहेंगे?", "action": "show_recommendations" },
      { "after_3_tools": "आप बहुत तेज़ हो! मज़े के लिए हमारा AI फेस स्वैप आज़माएं! 🔥", "action": "recommend_face_swap" },
      { "idle_30_seconds": "अटक गए? मदद चाहिए? Texly टूल्स के बारे में मुझसे कुछ भी पूछें! 💬", "action": "show_help" }
    ],
    "daily_tip_messages_en": [
      "💡 Tip: Use our compressors before uploading to social media!",
      "💡 Tip: Remove background from product photos for a clean look!",
      "💡 Tip: Count words before submitting essays to meet requirements!"
    ],
    "daily_tip_messages_hi": [
      "💡 टिप: सोशल मीडिया पर अपलोड करने से पहले हमारे कंप्रेसर का उपयोग करें!",
      "💡 टिप: क्लीन लुक के लिए प्रोडक्ट फोटो से बैकग्राउंड हटाएं!",
      "💡 टिप: आवश्यकताओं को पूरा करने के लिए निबंध जमा करने से पहले शब्द गिनें!"
    ]
  },
  "exit_intent_system": {
    "exit_messages_en": [
      "Wait! Before you go 👋 Found what you needed? I can help find the right tool!",
      "Leaving so soon? 😢 Come back anytime for free AI tools!",
      "Don't go! Your perfect tool is just a click away. Let me help you!"
    ],
    "exit_messages_hi": [
      "रुको! जाने से पहले 👋 आपको वह मिल गया जो चाहिए था? मैं सही टूल ढूंढने में मदद कर सकता हूँ!",
      "इतनी जल्दी जा रहे हो? 😢 मुफ्त AI टूल्स के लिए कभी भी वापस आएं!",
      "मत जाओ! आपका परफेक्ट टूल बस एक क्लिक दूर है। मुझे आपकी मदद करने दो!"
    ]
  },
  "language_support": {
    "supported_languages": ["en", "hi"],
    "auto_detect_from_input": true,
    "greetings": {
      "en": "Hello! How can I help you today?",
      "hi": "नमस्ते! आज मैं आपकी कैसे मदद कर सकता हूँ?"
    },
    "switch_to_hindi_message": "क्या आप हिंदी में मदद चाहेंगे?",
    "switch_to_english_message": "Would you like help in English?"
  }
}